Metadata-Version: 1.0
Name: probdistributions
Version: 0.1
Summary: Gaussian and Binomial distributions
Home-page: UNKNOWN
Author: Oluwaseyi Akinwande
Author-email: oia0001@auburn.edu
License: UNKNOWN
Platform: UNKNOWN
